hpe3parclient/__init__.py
hpe3parclient/client.py
hpe3parclient/exceptions.py
hpe3parclient/file_client.py
hpe3parclient/http.py
hpe3parclient/showport_parser.py
hpe3parclient/ssh.py
hpe3parclient/tcl_parser.py
hpe3parclient-4.2.13.dist-info/METADATA
hpe3parclient-4.2.13.dist-info/WHEEL
hpe3parclient-4.2.13.dist-info/licenses/LICENSE
hpe3parclient-4.2.13.dist-info/RECORD
