Metadata-Version: 2.1
Name: hpe3parclient
Version: 4.2.13
Summary: HPE Alletra 9000 and HPE Primera and HPE 3PAR REST Client
Author-email: Raghavendra Tilay <raghavendra-uddhav.tilay@hpe.com>
License-File: LICENSE
Classifier: Development Status :: 5 - Production/Stable
Classifier: Environment :: Web Environment
Classifier: Intended Audience :: Developers
Classifier: License :: OSI Approved :: Apache Software License
Classifier: Operating System :: OS Independent
Classifier: Programming Language :: Python
Classifier: Programming Language :: Python :: 2.7
Classifier: Programming Language :: Python :: 3.8
Classifier: Topic :: Internet :: WWW/HTTP
